LICENCE
MANIFEST.in
README.mkd
requirements.txt
setup.py
graphunc/__init__.py
graphunc/__main__.py
graphunc/commons.py
graphunc/graphunc.py
graphunc/info.py
graphunc/solving.py
graphunc/validator.py
graphunc.egg-info/PKG-INFO
graphunc.egg-info/SOURCES.txt
graphunc.egg-info/dependency_links.txt
graphunc.egg-info/requires.txt
graphunc.egg-info/top_level.txt
graphunc/test/__init__.py
graphunc/test/test_conspread.py
graphunc/test/test_solving.py